Metadata-Version: 1.0
Name: discord-embeds
Version: 0.4.beta
Summary: Package for make eazy embeds
Home-page: UNKNOWN
Author: UNKNOWN
Author-email: sashakilin12@gmail.com
License: UNKNOWN
Platform: UNKNOWN
